cdktf_cdktf_provider_ad/__init__.py
cdktf_cdktf_provider_ad/py.typed
cdktf_cdktf_provider_ad/_jsii/__init__.py
cdktf_cdktf_provider_ad/_jsii/provider-ad@8.0.1.jsii.tgz
cdktf_cdktf_provider_ad/computer/__init__.py
cdktf_cdktf_provider_ad/data_ad_computer/__init__.py
cdktf_cdktf_provider_ad/data_ad_gpo/__init__.py
cdktf_cdktf_provider_ad/data_ad_group/__init__.py
cdktf_cdktf_provider_ad/data_ad_ou/__init__.py
cdktf_cdktf_provider_ad/data_ad_user/__init__.py
cdktf_cdktf_provider_ad/gplink/__init__.py
cdktf_cdktf_provider_ad/gpo/__init__.py
cdktf_cdktf_provider_ad/gpo_security/__init__.py
cdktf_cdktf_provider_ad/group/__init__.py
cdktf_cdktf_provider_ad/group_membership/__init__.py
cdktf_cdktf_provider_ad/ou/__init__.py
cdktf_cdktf_provider_ad/provider/__init__.py
cdktf_cdktf_provider_ad/user/__init__.py
cdktf_cdktf_provider_ad-8.0.1.dist-info/LICENSE
cdktf_cdktf_provider_ad-8.0.1.dist-info/METADATA
cdktf_cdktf_provider_ad-8.0.1.dist-info/WHEEL
cdktf_cdktf_provider_ad-8.0.1.dist-info/top_level.txt
cdktf_cdktf_provider_ad-8.0.1.dist-info/RECORD
